<?xml version='1.0' encoding='windows-1252' ?>
<!DOCTYPE Entity SYSTEM "jbo_03_01.dtd">
<!---->

<Entity
   xmlns="http://xmlns.oracle.com/bc4j"
   Name="Ref_SoRefertomammo1liv"
   Version="12.2.1.11.57"
   DBObjectType="table"
   DBObjectName="SO_REFERTOMAMMO1LIV"
   AliasName="Ref_SoRefertomammo1liv"
   BindingStyle="Oracle"
   RowClass="model.referto.Ref_SoRefertomammo1livImpl" >
   <DesignTime>
      <Attr Name="_codeGenFlag2" Value="Access" />
      <Attr Name="_isCodegen" Value="true" />
   </DesignTime>
   <Attribute
      Name="Idreferto"
      IsNotNull="true"
      ColumnName="IDREFERTO"
      SQLType="NUMERIC"
      Type="java.lang.Integer"
      ColumnType="NUMBER"
      TableName="SO_REFERTOMAMMO1LIV"
      PrimaryKey="true" >
      <DesignTime>
         <Attr Name="_DisplaySize" Value="22" />
      </DesignTime>
   </Attribute>
   <Attribute
      Name="Idinvito"
      IsNotNull="true"
      ColumnName="IDINVITO"
      SQLType="NUMERIC"
      Type="java.lang.Integer"
      ColumnType="NUMBER"
      TableName="SO_REFERTOMAMMO1LIV" >
      <DesignTime>
         <Attr Name="_DisplaySize" Value="22" />
      </DesignTime>
   </Attribute>
   <Attribute
      Name="Codts"
      IsNotNull="true"
      Precision="11"
      ColumnName="CODTS"
      SQLType="VARCHAR"
      Type="java.lang.String"
      ColumnType="VARCHAR2"
      TableName="SO_REFERTOMAMMO1LIV" >
      <DesignTime>
         <Attr Name="_DisplaySize" Value="11" />
      </DesignTime>
   </Attribute>
   <Attribute
      Name="Ulss"
      IsNotNull="true"
      Precision="6"
      ColumnName="ULSS"
      SQLType="CHAR"
      Type="java.lang.String"
      ColumnType="CHAR"
      TableName="SO_REFERTOMAMMO1LIV"
      RetrievedOnUpdate="true"
      RetrievedOnInsert="true" >
      <DesignTime>
         <Attr Name="_DisplaySize" Value="6" />
      </DesignTime>
   </Attribute>
   <Attribute
      Name="Tpscr"
      IsNotNull="true"
      Precision="2"
      ColumnName="TPSCR"
      SQLType="CHAR"
      Type="java.lang.String"
      ColumnType="CHAR"
      TableName="SO_REFERTOMAMMO1LIV"
      RetrievedOnUpdate="true"
      RetrievedOnInsert="true" >
      <DesignTime>
         <Attr Name="_DisplaySize" Value="2" />
      </DesignTime>
   </Attribute>
   <Attribute
      Name="L1Radiologo"
      Precision="4"
      Scale="0"
      ColumnName="L1_RADIOLOGO"
      SQLType="NUMERIC"
      Type="java.lang.Integer"
      ColumnType="NUMBER"
      TableName="SO_REFERTOMAMMO1LIV" >
      <DesignTime>
         <Attr Name="_DisplaySize" Value="22" />
      </DesignTime>
   </Attribute>
   <Attribute
      Name="L1Esito"
      Precision="2"
      Scale="0"
      ColumnName="L1_ESITO"
      SQLType="NUMERIC"
      Type="java.lang.Integer"
      ColumnType="NUMBER"
      TableName="SO_REFERTOMAMMO1LIV" >
      <DesignTime>
         <Attr Name="_DisplaySize" Value="22" />
      </DesignTime>
   </Attribute>
   <Attribute
      Name="L1AltreIndicazioni"
      Precision="300"
      ColumnName="L1_ALTRE_INDICAZIONI"
      SQLType="VARCHAR"
      Type="java.lang.String"
      ColumnType="VARCHAR2"
      TableName="SO_REFERTOMAMMO1LIV" >
      <DesignTime>
         <Attr Name="_DisplaySize" Value="300" />
      </DesignTime>
   </Attribute>
   <Attribute
      Name="L1Note"
      Precision="300"
      ColumnName="L1_NOTE"
      SQLType="VARCHAR"
      Type="java.lang.String"
      ColumnType="VARCHAR2"
      TableName="SO_REFERTOMAMMO1LIV" >
      <DesignTime>
         <Attr Name="_DisplaySize" Value="300" />
      </DesignTime>
   </Attribute>
   <Attribute
      Name="L2Radiologo"
      Precision="4"
      Scale="0"
      ColumnName="L2_RADIOLOGO"
      SQLType="NUMERIC"
      Type="java.lang.Integer"
      ColumnType="NUMBER"
      TableName="SO_REFERTOMAMMO1LIV" >
      <DesignTime>
         <Attr Name="_DisplaySize" Value="22" />
      </DesignTime>
   </Attribute>
   <Attribute
      Name="L2Esito"
      Precision="2"
      Scale="0"
      ColumnName="L2_ESITO"
      SQLType="NUMERIC"
      Type="java.lang.Integer"
      ColumnType="NUMBER"
      TableName="SO_REFERTOMAMMO1LIV" >
      <DesignTime>
         <Attr Name="_DisplaySize" Value="22" />
      </DesignTime>
   </Attribute>
   <Attribute
      Name="L2AltreIndicazioni"
      Precision="300"
      ColumnName="L2_ALTRE_INDICAZIONI"
      SQLType="VARCHAR"
      Type="java.lang.String"
      ColumnType="VARCHAR2"
      TableName="SO_REFERTOMAMMO1LIV" >
      <DesignTime>
         <Attr Name="_DisplaySize" Value="300" />
      </DesignTime>
   </Attribute>
   <Attribute
      Name="L2Note"
      Precision="300"
      ColumnName="L2_NOTE"
      SQLType="VARCHAR"
      Type="java.lang.String"
      ColumnType="VARCHAR2"
      TableName="SO_REFERTOMAMMO1LIV" >
      <DesignTime>
         <Attr Name="_DisplaySize" Value="300" />
      </DesignTime>
   </Attribute>
   <Attribute
      Name="RRadiologo"
      Precision="4"
      Scale="0"
      ColumnName="R_RADIOLOGO"
      SQLType="NUMERIC"
      Type="java.lang.Integer"
      ColumnType="NUMBER"
      TableName="SO_REFERTOMAMMO1LIV" >
      <DesignTime>
         <Attr Name="_DisplaySize" Value="22" />
      </DesignTime>
   </Attribute>
   <Attribute
      Name="REsito"
      Precision="2"
      Scale="0"
      ColumnName="R_ESITO"
      SQLType="NUMERIC"
      Type="java.lang.Integer"
      ColumnType="NUMBER"
      TableName="SO_REFERTOMAMMO1LIV" >
      <DesignTime>
         <Attr Name="_DisplaySize" Value="22" />
      </DesignTime>
   </Attribute>
   <Attribute
      Name="RAltreIndicazioni"
      Precision="300"
      ColumnName="R_ALTRE_INDICAZIONI"
      SQLType="VARCHAR"
      Type="java.lang.String"
      ColumnType="VARCHAR2"
      TableName="SO_REFERTOMAMMO1LIV" >
      <DesignTime>
         <Attr Name="_DisplaySize" Value="300" />
      </DesignTime>
   </Attribute>
   <Attribute
      Name="RNote"
      Precision="300"
      ColumnName="R_NOTE"
      SQLType="VARCHAR"
      Type="java.lang.String"
      ColumnType="VARCHAR2"
      TableName="SO_REFERTOMAMMO1LIV" >
      <DesignTime>
         <Attr Name="_DisplaySize" Value="300" />
      </DesignTime>
   </Attribute>
   <Attribute
      Name="Idsugg"
      Precision="3"
      Scale="0"
      ColumnName="IDSUGG"
      SQLType="NUMERIC"
      Type="java.lang.Integer"
      ColumnType="NUMBER"
      TableName="SO_REFERTOMAMMO1LIV" >
      <DesignTime>
         <Attr Name="_DisplaySize" Value="22" />
      </DesignTime>
   </Attribute>
   <Attribute
      Name="Dtreferto"
      ColumnName="DTREFERTO"
      SQLType="DATE"
      Type="oracle.jbo.domain.Date"
      ColumnType="DATE"
      TableName="SO_REFERTOMAMMO1LIV" >
      <DesignTime>
         <Attr Name="_DisplaySize" Value="7" />
      </DesignTime>
   </Attribute>
   <Attribute
      Name="Completo"
      Precision="1"
      Scale="0"
      ColumnName="COMPLETO"
      SQLType="NUMERIC"
      Type="java.lang.Integer"
      ColumnType="NUMBER"
      TableName="SO_REFERTOMAMMO1LIV" >
      <DesignTime>
         <Attr Name="_DisplaySize" Value="22" />
      </DesignTime>
   </Attribute>
   <Attribute
      Name="Dtinserimento"
      IsNotNull="true"
      ColumnName="DTINSERIMENTO"
      SQLType="DATE"
      Type="oracle.jbo.domain.Date"
      ColumnType="DATE"
      TableName="SO_REFERTOMAMMO1LIV" >
      <DesignTime>
         <Attr Name="_DisplaySize" Value="7" />
      </DesignTime>
   </Attribute>
   <Attribute
      Name="Opinserimento"
      IsNotNull="true"
      Precision="50"
      ColumnName="OPINSERIMENTO"
      SQLType="VARCHAR"
      Type="java.lang.String"
      ColumnType="VARCHAR2"
      TableName="SO_REFERTOMAMMO1LIV" >
      <DesignTime>
         <Attr Name="_DisplaySize" Value="50" />
      </DesignTime>
   </Attribute>
   <Attribute
      Name="Dtultmodifica"
      ColumnName="DTULTMODIFICA"
      SQLType="DATE"
      Type="oracle.jbo.domain.Date"
      ColumnType="DATE"
      TableName="SO_REFERTOMAMMO1LIV" >
      <DesignTime>
         <Attr Name="_DisplaySize" Value="7" />
      </DesignTime>
   </Attribute>
   <Attribute
      Name="Opultmodifica"
      Precision="50"
      ColumnName="OPULTMODIFICA"
      SQLType="VARCHAR"
      Type="java.lang.String"
      ColumnType="VARCHAR2"
      TableName="SO_REFERTOMAMMO1LIV" >
      <DesignTime>
         <Attr Name="_DisplaySize" Value="50" />
      </DesignTime>
   </Attribute>
   <Attribute
      Name="Tpreferto"
      IsNotNull="true"
      Precision="1"
      Scale="0"
      ColumnName="TPREFERTO"
      SQLType="NUMERIC"
      Type="java.lang.Integer"
      ColumnType="NUMBER"
      TableName="SO_REFERTOMAMMO1LIV" >
      <DesignTime>
         <Attr Name="_DisplaySize" Value="22" />
      </DesignTime>
   </Attribute>
   <Attribute
      Name="Idallegato"
      ColumnName="IDALLEGATO"
      SQLType="NUMERIC"
      Type="java.lang.Integer"
      ColumnType="NUMBER"
      TableName="SO_REFERTOMAMMO1LIV" >
      <DesignTime>
         <Attr Name="_DisplaySize" Value="22" />
      </DesignTime>
   </Attribute>
   <Attribute
      Name="Dtcreazione"
      ColumnName="DTCREAZIONE"
      SQLType="DATE"
      Type="oracle.jbo.domain.Date"
      ColumnType="DATE"
      TableName="SO_REFERTOMAMMO1LIV" >
      <DesignTime>
         <Attr Name="_DisplaySize" Value="7" />
      </DesignTime>
   </Attribute>
   <Attribute
      Name="Dtspedizione"
      ColumnName="DTSPEDIZIONE"
      SQLType="DATE"
      Type="oracle.jbo.domain.Date"
      ColumnType="DATE"
      TableName="SO_REFERTOMAMMO1LIV" >
      <DesignTime>
         <Attr Name="_DisplaySize" Value="7" />
      </DesignTime>
   </Attribute>
   <Attribute
      Name="CodiceReferto"
      Precision="50"
      ColumnName="CODICE_REFERTO"
      SQLType="VARCHAR"
      Type="java.lang.String"
      ColumnType="VARCHAR2"
      TableName="SO_REFERTOMAMMO1LIV" >
      <DesignTime>
         <Attr Name="_DisplaySize" Value="50" />
      </DesignTime>
   </Attribute>
   <Attribute
      Name="Idcentroref"
      Precision="4"
      Scale="0"
      ColumnName="IDCENTROREF"
      SQLType="NUMERIC"
      Type="java.lang.Integer"
      ColumnType="NUMBER"
      TableName="SO_REFERTOMAMMO1LIV" >
      <DesignTime>
         <Attr Name="_DisplaySize" Value="22" />
      </DesignTime>
   </Attribute>
   <Attribute
      Name="GrEsito"
      Precision="6"
      ColumnName="GR_ESITO"
      SQLType="CHAR"
      Type="java.lang.String"
      ColumnType="CHAR"
      TableName="SO_REFERTOMAMMO1LIV"
      RetrievedOnUpdate="true"
      RetrievedOnInsert="true" >
      <DesignTime>
         <Attr Name="_DisplaySize" Value="6" />
      </DesignTime>
   </Attribute>
   <Attribute
      Name="L1Sugg"
      Precision="3"
      Scale="0"
      ColumnName="L1_SUGG"
      SQLType="NUMERIC"
      Type="java.lang.Integer"
      ColumnType="NUMBER"
      TableName="SO_REFERTOMAMMO1LIV" >
      <DesignTime>
         <Attr Name="_DisplaySize" Value="22" />
      </DesignTime>
   </Attribute>
   <Attribute
      Name="L2Sugg"
      Precision="3"
      Scale="0"
      ColumnName="L2_SUGG"
      SQLType="NUMERIC"
      Type="java.lang.Integer"
      ColumnType="NUMBER"
      TableName="SO_REFERTOMAMMO1LIV" >
      <DesignTime>
         <Attr Name="_DisplaySize" Value="22" />
      </DesignTime>
   </Attribute>
   <Attribute
      Name="Revisione"
      Precision="1"
      Scale="0"
      ColumnName="REVISIONE"
      SQLType="NUMERIC"
      Type="java.lang.Integer"
      ColumnType="NUMBER"
      TableName="SO_REFERTOMAMMO1LIV" >
      <DesignTime>
         <Attr Name="_DisplaySize" Value="22" />
      </DesignTime>
   </Attribute>
   <Attribute
      Name="RSugg"
      Precision="3"
      Scale="0"
      ColumnName="R_SUGG"
      SQLType="NUMERIC"
      Type="java.lang.Integer"
      ColumnType="NUMBER"
      TableName="SO_REFERTOMAMMO1LIV" >
      <DesignTime>
         <Attr Name="_DisplaySize" Value="22" />
      </DesignTime>
   </Attribute>
   <Attribute
      Name="Esito"
      Precision="2"
      Scale="0"
      ColumnName="ESITO"
      SQLType="NUMERIC"
      Type="java.lang.Integer"
      ColumnType="NUMBER"
      TableName="SO_REFERTOMAMMO1LIV" >
      <DesignTime>
         <Attr Name="_DisplaySize" Value="22" />
      </DesignTime>
   </Attribute>
   <Attribute
      Name="Dtmammo"
      ColumnName="DTMAMMO"
      SQLType="DATE"
      Type="oracle.jbo.domain.Date"
      ColumnType="DATE"
      TableName="SO_REFERTOMAMMO1LIV" >
      <DesignTime>
         <Attr Name="_DisplaySize" Value="7" />
      </DesignTime>
   </Attribute>
   <Attribute
      Name="L1Idcentroref"
      Precision="4"
      Scale="0"
      ColumnName="L1_IDCENTROREF"
      SQLType="NUMERIC"
      Type="java.lang.Integer"
      ColumnType="NUMBER"
      TableName="SO_REFERTOMAMMO1LIV"/>
   <Attribute
      Name="L2Idcentroref"
      Precision="4"
      Scale="0"
      ColumnName="L2_IDCENTROREF"
      SQLType="NUMERIC"
      Type="java.lang.Integer"
      ColumnType="NUMBER"
      TableName="SO_REFERTOMAMMO1LIV"/>
   <Attribute
      Name="RIdcentroref"
      Precision="4"
      Scale="0"
      ColumnName="R_IDCENTROREF"
      SQLType="NUMERIC"
      Type="java.lang.Integer"
      ColumnType="NUMBER"
      TableName="SO_REFERTOMAMMO1LIV"/>
   <Attribute
      Name="Densita"
      Precision="1"
      Scale="0"
      ColumnName="DENSITA"
      SQLType="NUMERIC"
      Type="java.lang.Integer"
      ColumnType="NUMBER"
      TableName="SO_REFERTOMAMMO1LIV"/>
   <AccessorAttribute
      Name="A_SoOpmedico"
      Association="model.FkRefmammo1lHaLettore1Assoc"
      AssociationEnd="model.FkRefmammo1lHaLettore1Assoc.A_SoOpmedico"
      AssociationOtherEnd="model.FkRefmammo1lHaLettore1Assoc.Ref_SoRefertomammo1liv"
      Type="model.global.A_SoOpmedicoImpl"
      IsUpdateable="true">
   </AccessorAttribute>
   <AccessorAttribute
      Name="A_SoOpmedico1"
      Association="model.FkRefmammo1lHaRevisoreAssoc"
      AssociationEnd="model.FkRefmammo1lHaRevisoreAssoc.A_SoOpmedico1"
      AssociationOtherEnd="model.FkRefmammo1lHaRevisoreAssoc.Ref_SoRefertomammo1liv1"
      Type="model.global.A_SoOpmedicoImpl"
      IsUpdateable="true">
   </AccessorAttribute>
   <AccessorAttribute
      Name="A_SoOpmedico2"
      Association="model.FkRefmammoilHaLettore2Assoc"
      AssociationEnd="model.FkRefmammoilHaLettore2Assoc.A_SoOpmedico2"
      AssociationOtherEnd="model.FkRefmammoilHaLettore2Assoc.Ref_SoRefertomammo1liv2"
      Type="model.global.A_SoOpmedicoImpl"
      IsUpdateable="true">
   </AccessorAttribute>
   <Key
      Name="PkSoRefMammo1liv"
      PrimaryKey="true" >
      <DesignTime>
         <Attr Name="_DBObjectName" Value="PK_SO_REF_MAMMO1LIV"/>
      </DesignTime>
      <AttrArray Name="Attributes">
         <Item Value="model.referto.Ref_SoRefertomammo1liv.Idreferto" />
      </AttrArray>
   </Key>
   <Key
      Name="FkRefmammo1lHaAllegato" >
      <DesignTime>
         <Attr Name="_referencedKey" Value="PK_SO_ALLEGATO"/>
         <Attr Name="_isForeign" Value="true"/>
         <Attr Name="_DBObjectName" Value="FK_REFMAMMO1L_HA_ALLEGATO"/>
      </DesignTime>
      <AttrArray Name="Attributes">
         <Item Value="model.referto.Ref_SoRefertomammo1liv.Idallegato" />
      </AttrArray>
   </Key>
   <Key
      Name="FkRefmammo1lHaEsito" >
      <DesignTime>
         <Attr Name="_referencedKey" Value="PK_SO_CNF_POSREF1LIV"/>
         <Attr Name="_isForeign" Value="true"/>
         <Attr Name="_DBObjectName" Value="FK_REFMAMMO1L_HA_ESITO"/>
      </DesignTime>
      <AttrArray Name="Attributes">
         <Item Value="model.referto.Ref_SoRefertomammo1liv.Esito" />
         <Item Value="model.referto.Ref_SoRefertomammo1liv.GrEsito" />
         <Item Value="model.referto.Ref_SoRefertomammo1liv.Tpscr" />
         <Item Value="model.referto.Ref_SoRefertomammo1liv.Ulss" />
      </AttrArray>
   </Key>
   <Key
      Name="FkRefmammo1lHaEsito1" >
      <DesignTime>
         <Attr Name="_referencedKey" Value="PK_SO_CNF_POSREF1LIV"/>
         <Attr Name="_isForeign" Value="true"/>
         <Attr Name="_DBObjectName" Value="FK_REFMAMMO1L_HA_ESITO_1"/>
      </DesignTime>
      <AttrArray Name="Attributes">
         <Item Value="model.referto.Ref_SoRefertomammo1liv.L1Esito" />
         <Item Value="model.referto.Ref_SoRefertomammo1liv.GrEsito" />
         <Item Value="model.referto.Ref_SoRefertomammo1liv.Tpscr" />
         <Item Value="model.referto.Ref_SoRefertomammo1liv.Ulss" />
      </AttrArray>
   </Key>
   <Key
      Name="FkRefmammo1lHaEsito2" >
      <DesignTime>
         <Attr Name="_referencedKey" Value="PK_SO_CNF_POSREF1LIV"/>
         <Attr Name="_isForeign" Value="true"/>
         <Attr Name="_DBObjectName" Value="FK_REFMAMMO1L_HA_ESITO_2"/>
      </DesignTime>
      <AttrArray Name="Attributes">
         <Item Value="model.referto.Ref_SoRefertomammo1liv.L2Esito" />
         <Item Value="model.referto.Ref_SoRefertomammo1liv.GrEsito" />
         <Item Value="model.referto.Ref_SoRefertomammo1liv.Tpscr" />
         <Item Value="model.referto.Ref_SoRefertomammo1liv.Ulss" />
      </AttrArray>
   </Key>
   <Key
      Name="FkRefmammo1lHaEsitoR" >
      <DesignTime>
         <Attr Name="_referencedKey" Value="PK_SO_CNF_POSREF1LIV"/>
         <Attr Name="_isForeign" Value="true"/>
         <Attr Name="_DBObjectName" Value="FK_REFMAMMO1L_HA_ESITO_R"/>
      </DesignTime>
      <AttrArray Name="Attributes">
         <Item Value="model.referto.Ref_SoRefertomammo1liv.REsito" />
         <Item Value="model.referto.Ref_SoRefertomammo1liv.GrEsito" />
         <Item Value="model.referto.Ref_SoRefertomammo1liv.Tpscr" />
         <Item Value="model.referto.Ref_SoRefertomammo1liv.Ulss" />
      </AttrArray>
   </Key>
   <Key
      Name="FkRefmammo1lHaLettore1" >
      <DesignTime>
         <Attr Name="_referencedKey" Value="PK_SO_OPMEDICO"/>
         <Attr Name="_isForeign" Value="true"/>
         <Attr Name="_DBObjectName" Value="FK_REFMAMMO1L_HA_LETTORE1"/>
      </DesignTime>
      <AttrArray Name="Attributes">
         <Item Value="model.referto.Ref_SoRefertomammo1liv.L1Radiologo" />
      </AttrArray>
   </Key>
   <Key
      Name="FkRefmammo1lHaRevisore" >
      <DesignTime>
         <Attr Name="_referencedKey" Value="PK_SO_OPMEDICO"/>
         <Attr Name="_isForeign" Value="true"/>
         <Attr Name="_DBObjectName" Value="FK_REFMAMMO1L_HA_REVISORE"/>
      </DesignTime>
      <AttrArray Name="Attributes">
         <Item Value="model.referto.Ref_SoRefertomammo1liv.RRadiologo" />
      </AttrArray>
   </Key>
   <Key
      Name="FkRefmammo1lHaSogg" >
      <DesignTime>
         <Attr Name="_referencedKey" Value="PK_SO_SOGGETTO"/>
         <Attr Name="_isForeign" Value="true"/>
         <Attr Name="_DBObjectName" Value="FK_REFMAMMO1L_HA_SOGG"/>
      </DesignTime>
      <AttrArray Name="Attributes">
         <Item Value="model.referto.Ref_SoRefertomammo1liv.Codts" />
         <Item Value="model.referto.Ref_SoRefertomammo1liv.Ulss" />
      </AttrArray>
   </Key>
   <Key
      Name="FkRefmammo1lHaSugg" >
      <DesignTime>
         <Attr Name="_referencedKey" Value="PK_SO_CNF_SUGG_1LIV"/>
         <Attr Name="_isForeign" Value="true"/>
         <Attr Name="_DBObjectName" Value="FK_REFMAMMO1L_HA_SUGG"/>
      </DesignTime>
      <AttrArray Name="Attributes">
         <Item Value="model.referto.Ref_SoRefertomammo1liv.Idsugg" />
         <Item Value="model.referto.Ref_SoRefertomammo1liv.Ulss" />
         <Item Value="model.referto.Ref_SoRefertomammo1liv.Tpscr" />
      </AttrArray>
   </Key>
   <Key
      Name="FkRefmammo1lHaSugg1" >
      <DesignTime>
         <Attr Name="_isForeign" Value="true"/>
         <Attr Name="_DBObjectName" Value="FK_REFMAMMO1L_HA_SUGG1"/>
         <Attr Name="_referencedKey" Value="PK_SO_CNF_SUGG_1LIV"/>
      </DesignTime>
      <AttrArray Name="Attributes">
         <Item Value="model.referto.Ref_SoRefertomammo1liv.L1Sugg" />
         <Item Value="model.referto.Ref_SoRefertomammo1liv.Ulss" />
         <Item Value="model.referto.Ref_SoRefertomammo1liv.Tpscr" />
      </AttrArray>
   </Key>
   <Key
      Name="FkRefmammo1lHaSugg2" >
      <DesignTime>
         <Attr Name="_isForeign" Value="true"/>
         <Attr Name="_DBObjectName" Value="FK_REFMAMMO1L_HA_SUGG2"/>
         <Attr Name="_referencedKey" Value="PK_SO_CNF_SUGG_1LIV"/>
      </DesignTime>
      <AttrArray Name="Attributes">
         <Item Value="model.referto.Ref_SoRefertomammo1liv.L2Sugg" />
         <Item Value="model.referto.Ref_SoRefertomammo1liv.Ulss" />
         <Item Value="model.referto.Ref_SoRefertomammo1liv.Tpscr" />
      </AttrArray>
   </Key>
   <Key
      Name="FkRefmammo1lHaSuggR" >
      <DesignTime>
         <Attr Name="_isForeign" Value="true"/>
         <Attr Name="_DBObjectName" Value="FK_REFMAMMO1L_HA_SUGG_R"/>
         <Attr Name="_referencedKey" Value="PK_SO_CNF_SUGG_1LIV"/>
      </DesignTime>
      <AttrArray Name="Attributes">
         <Item Value="model.referto.Ref_SoRefertomammo1liv.RSugg" />
         <Item Value="model.referto.Ref_SoRefertomammo1liv.Ulss" />
         <Item Value="model.referto.Ref_SoRefertomammo1liv.Tpscr" />
      </AttrArray>
   </Key>
   <Key
      Name="FkRefmammo1livCentro" >
      <DesignTime>
         <Attr Name="_referencedKey" Value="PK_SO_CENTRO_PREL_REF"/>
         <Attr Name="_isForeign" Value="true"/>
         <Attr Name="_DBObjectName" Value="FK_REFMAMMO1LIV_CENTRO"/>
      </DesignTime>
      <AttrArray Name="Attributes">
         <Item Value="model.referto.Ref_SoRefertomammo1liv.Idcentroref" />
      </AttrArray>
   </Key>
   <Key
      Name="FkRefmammoilHaLettore2" >
      <DesignTime>
         <Attr Name="_referencedKey" Value="PK_SO_OPMEDICO"/>
         <Attr Name="_isForeign" Value="true"/>
         <Attr Name="_DBObjectName" Value="FK_REFMAMMOIL_HA_LETTORE2"/>
      </DesignTime>
      <AttrArray Name="Attributes">
         <Item Value="model.referto.Ref_SoRefertomammo1liv.L2Radiologo" />
      </AttrArray>
   </Key>
</Entity>
